{
"meta":{"test_sets":[],"test_metrics":[],"learn_metrics":[{"best_value":"Min","name":"RMSE"}],"launch_mode":"Train","parameters":"","iteration_count":100,"learn_sets":["learn"],"name":"experiment"},
"iterations":[
{"learn":[14.005006],"iteration":0,"passed_time":0.002031735071,"remaining_time":0.201141772},
{"learn":[13.14441192],"iteration":1,"passed_time":0.003772869018,"remaining_time":0.1848705819},
{"learn":[12.34258257],"iteration":2,"passed_time":0.005478084238,"remaining_time":0.1771247237},
{"learn":[11.64527793],"iteration":3,"passed_time":0.006841614167,"remaining_time":0.16419874},
{"learn":[11.02766183],"iteration":4,"passed_time":0.008541070708,"remaining_time":0.1622803435},
{"learn":[10.43485794],"iteration":5,"passed_time":0.0102252541,"remaining_time":0.1601956476},
{"learn":[9.890641275],"iteration":6,"passed_time":0.01198640541,"remaining_time":0.1592479575},
{"learn":[9.492161212],"iteration":7,"passed_time":0.01366472642,"remaining_time":0.1571443538},
{"learn":[9.105082953],"iteration":8,"passed_time":0.01538076765,"remaining_time":0.1555166507},
{"learn":[8.674157135],"iteration":9,"passed_time":0.01713018819,"remaining_time":0.1541716937},
{"learn":[8.341743544],"iteration":10,"passed_time":0.01885942003,"remaining_time":0.152589853},
{"learn":[8.049372916],"iteration":11,"passed_time":0.02062358568,"remaining_time":0.1512396284},
{"learn":[7.757318612],"iteration":12,"passed_time":0.02227693272,"remaining_time":0.1490840882},
{"learn":[7.522206899],"iteration":13,"passed_time":0.02396312952,"remaining_time":0.1472020813},
{"learn":[7.297756655],"iteration":14,"passed_time":0.02566878058,"remaining_time":0.1454564233},
{"learn":[7.088359431],"iteration":15,"passed_time":0.02728476809,"remaining_time":0.1432450325},
{"learn":[6.882113791],"iteration":16,"passed_time":0.02897595558,"remaining_time":0.1414708419},
{"learn":[6.704728832],"iteration":17,"passed_time":0.03076945919,"remaining_time":0.1401719807},
{"learn":[6.563881962],"iteration":18,"passed_time":0.03275498305,"remaining_time":0.1396396646},
{"learn":[6.418790279],"iteration":19,"passed_time":0.03485624058,"remaining_time":0.1394249623},
{"learn":[6.315756953],"iteration":20,"passed_time":0.03680764672,"remaining_time":0.1384668615},
{"learn":[6.210157751],"iteration":21,"passed_time":0.03835476002,"remaining_time":0.1359850583},
{"learn":[6.115058449],"iteration":22,"passed_time":0.03955700737,"remaining_time":0.1324299812},
{"learn":[6.014819884],"iteration":23,"passed_time":0.04074393547,"remaining_time":0.1290224623},
{"learn":[5.93117229],"iteration":24,"passed_time":0.04207668916,"remaining_time":0.1262300675},
{"learn":[5.844857622],"iteration":25,"passed_time":0.04337878633,"remaining_time":0.1234626996},
{"learn":[5.771145213],"iteration":26,"passed_time":0.04460287958,"remaining_time":0.1205929707},
{"learn":[5.704018229],"iteration":27,"passed_time":0.0460511956,"remaining_time":0.1184173601},
{"learn":[5.665806474],"iteration":28,"passed_time":0.04734307394,"remaining_time":0.1159089052},
{"learn":[5.616500369],"iteration":29,"passed_time":0.04870162269,"remaining_time":0.1136371196},
{"learn":[5.558023666],"iteration":30,"passed_time":0.05001954008,"remaining_time":0.111333815},
{"learn":[5.510080976],"iteration":31,"passed_time":0.05132846751,"remaining_time":0.1090729935},
{"learn":[5.468747792],"iteration":32,"passed_time":0.05255148868,"remaining_time":0.1066954467},
{"learn":[5.429275534],"iteration":33,"passed_time":0.05390183301,"remaining_time":0.10463297},
{"learn":[5.402117324],"iteration":34,"passed_time":0.05518256471,"remaining_time":0.1024819059},
{"learn":[5.367635151],"iteration":35,"passed_time":0.05651333355,"remaining_time":0.1004681485},
{"learn":[5.345181232],"iteration":36,"passed_time":0.05772330438,"remaining_time":0.09828562638},
{"learn":[5.319151269],"iteration":37,"passed_time":0.05909591794,"remaining_time":0.09641965559},
{"learn":[5.296134146],"iteration":38,"passed_time":0.06036940257,"remaining_time":0.09442393736},
{"learn":[5.269629003],"iteration":39,"passed_time":0.06166900641,"remaining_time":0.09250350961},
{"learn":[5.251147059],"iteration":40,"passed_time":0.06295156866,"remaining_time":0.09058884271},
{"learn":[5.248003302],"iteration":41,"passed_time":0.06355451562,"remaining_time":0.08776575967},
{"learn":[5.232376509],"iteration":42,"passed_time":0.06489077611,"remaining_time":0.08601800555},
{"learn":[5.213524255],"iteration":43,"passed_time":0.06623363391,"remaining_time":0.08429735225},
{"learn":[5.189691584],"iteration":44,"passed_time":0.06747777959,"remaining_time":0.08247284172},
{"learn":[5.166052198],"iteration":45,"passed_time":0.06873481679,"remaining_time":0.08068869797},
{"learn":[5.140406659],"iteration":46,"passed_time":0.07022216208,"remaining_time":0.0791866934},
{"learn":[5.118929684],"iteration":47,"passed_time":0.07163336204,"remaining_time":0.07760280888},
{"learn":[5.108792602],"iteration":48,"passed_time":0.07287160777,"remaining_time":0.0758459591},
{"learn":[5.098141225],"iteration":49,"passed_time":0.07428524697,"remaining_time":0.07428524697},
{"learn":[5.085926393],"iteration":50,"passed_time":0.07574185358,"remaining_time":0.07277158481},
{"learn":[5.067816804],"iteration":51,"passed_time":0.07716648663,"remaining_time":0.07123060304},
{"learn":[5.049834901],"iteration":52,"passed_time":0.07862744118,"remaining_time":0.06972622142},
{"learn":[5.03838627],"iteration":53,"passed_time":0.08011464569,"remaining_time":0.06824580929},
{"learn":[5.033534248],"iteration":54,"passed_time":0.08108351199,"remaining_time":0.06634105526},
{"learn":[5.023726885],"iteration":55,"passed_time":0.08247049043,"remaining_time":0.06479824248},
{"learn":[5.01290392],"iteration":56,"passed_time":0.08393861491,"remaining_time":0.063322113},
{"learn":[5.005569127],"iteration":57,"passed_time":0.0853482849,"remaining_time":0.06180393045},
{"learn":[4.989969032],"iteration":58,"passed_time":0.08679192234,"remaining_time":0.06031303078},
{"learn":[4.976762446],"iteration":59,"passed_time":0.08833508197,"remaining_time":0.05889005465},
{"learn":[4.967222715],"iteration":60,"passed_time":0.08986502294,"remaining_time":0.0574546868},
{"learn":[4.954407599],"iteration":61,"passed_time":0.09131798548,"remaining_time":0.05596908788},
{"learn":[4.942125056],"iteration":62,"passed_time":0.09273692347,"remaining_time":0.05446454236},
{"learn":[4.930230716],"iteration":63,"passed_time":0.09420175355,"remaining_time":0.05298848637},
{"learn":[4.921695642],"iteration":64,"passed_time":0.09568659397,"remaining_time":0.0515235506},
{"learn":[4.906405625],"iteration":65,"passed_time":0.09716327205,"remaining_time":0.05005380681},
{"learn":[4.894330248],"iteration":66,"passed_time":0.09863936098,"remaining_time":0.04858356585},
{"learn":[4.88211557],"iteration":67,"passed_time":0.1001198815,"remaining_time":0.04711523836},
{"learn":[4.877946398],"iteration":68,"passed_time":0.1017850229,"remaining_time":0.04572950306},
{"learn":[4.863182126],"iteration":69,"passed_time":0.1034323508,"remaining_time":0.04432815034},
{"learn":[4.84646533],"iteration":70,"passed_time":0.105091452,"remaining_time":0.04292467757},
{"learn":[4.838014752],"iteration":71,"passed_time":0.1067315037,"remaining_time":0.04150669589},
{"learn":[4.82981137],"iteration":72,"passed_time":0.1083446327,"remaining_time":0.04007267236},
{"learn":[4.817094767],"iteration":73,"passed_time":0.1100195686,"remaining_time":0.03865552411},
{"learn":[4.808314151],"iteration":74,"passed_time":0.1118000319,"remaining_time":0.0372666773},
{"learn":[4.796235023],"iteration":75,"passed_time":0.1137879459,"remaining_time":0.03593303555},
{"learn":[4.784434534],"iteration":76,"passed_time":0.1158449024,"remaining_time":0.03460302281},
{"learn":[4.774402487],"iteration":77,"passed_time":0.1181026638,"remaining_time":0.03331100773},
{"learn":[4.76731896],"iteration":78,"passed_time":0.1197766534,"remaining_time":0.03183936356},
{"learn":[4.75934113],"iteration":79,"passed_time":0.1215430724,"remaining_time":0.0303857681},
{"learn":[4.754106378],"iteration":80,"passed_time":0.1232514057,"remaining_time":0.02891082356},
{"learn":[4.744002932],"iteration":81,"passed_time":0.1249832551,"remaining_time":0.02743534868},
{"learn":[4.731700554],"iteration":82,"passed_time":0.1266588583,"remaining_time":0.02594217581},
{"learn":[4.723284153],"iteration":83,"passed_time":0.1283198327,"remaining_time":0.02444187289},
{"learn":[4.712232782],"iteration":84,"passed_time":0.1302246479,"remaining_time":0.02298082021},
{"learn":[4.703046867],"iteration":85,"passed_time":0.1321352243,"remaining_time":0.02151038534},
{"learn":[4.698601855],"iteration":86,"passed_time":0.1339494731,"remaining_time":0.02001543851},
{"learn":[4.692429407],"iteration":87,"passed_time":0.1355622299,"remaining_time":0.01848575862},
{"learn":[4.675027364],"iteration":88,"passed_time":0.1372878918,"remaining_time":0.0169681664},
{"learn":[4.662368584],"iteration":89,"passed_time":0.1390631981,"remaining_time":0.01545146645},
{"learn":[4.646206172],"iteration":90,"passed_time":0.1408614028,"remaining_time":0.01393134753},
{"learn":[4.641245848],"iteration":91,"passed_time":0.1425068295,"remaining_time":0.01239189821},
{"learn":[4.633900435],"iteration":92,"passed_time":0.1441947661,"remaining_time":0.01085336949},
{"learn":[4.624738236],"iteration":93,"passed_time":0.1458307885,"remaining_time":0.009308348204},
{"learn":[4.612798287],"iteration":94,"passed_time":0.1474978652,"remaining_time":0.007763045538},
{"learn":[4.605222001],"iteration":95,"passed_time":0.149102921,"remaining_time":0.006212621709},
{"learn":[4.601725912],"iteration":96,"passed_time":0.150743906,"remaining_time":0.004662182661},
{"learn":[4.59722371],"iteration":97,"passed_time":0.1522687957,"remaining_time":0.003107526443},
{"learn":[4.580235665],"iteration":98,"passed_time":0.1538780351,"remaining_time":0.001554323587},
{"learn":[4.57591791],"iteration":99,"passed_time":0.1555973803,"remaining_time":0}
]}